{
  "usableSessionsCount": 3,
  "retiredSessionsCount": 0,
  "sessions": [
    {
      "id": "session_UHbbQJtmrw",
      "cookieJar": {
        "version": "tough-cookie@5.1.2",
        "storeType": "MemoryCookieStore",
        "rejectPublicSuffixes": true,
        "enableLooseMode": false,
        "allowSpecialUseDomain": true,
        "prefixSecurity": "silent",
        "cookies": []
      },
      "userData": {},
      "maxErrorScore": 3,
      "errorScoreDecrement": 0.5,
      "expiresAt": "2025-03-05T16:12:21.617Z",
      "createdAt": "2025-03-05T15:22:21.617Z",
      "usageCount": 0,
      "maxUsageCount": 50,
      "errorScore": 0
    },
    {
      "id": "session_17Le7idKkD",
      "cookieJar": {
        "version": "tough-cookie@5.1.2",
        "storeType": "MemoryCookieStore",
        "rejectPublicSuffixes": true,
        "enableLooseMode": false,
        "allowSpecialUseDomain": true,
        "prefixSecurity": "silent",
        "cookies": [
          {
            "key": "_cfuvid",
            "value": "_lY8uKd83RuFkxziPoOhCeVPIwDw8t.AIK9QkOYSetY-1741188143475-0.0.1.1-604800000",
            "expires": "2025-03-05T16:12:24.546Z",
            "domain": "upwork.com",
            "path": "/",
            "secure": true,
            "httpOnly": true,
            "hostOnly": false,
            "creation": "2025-03-05T15:22:24.549Z",
            "lastAccessed": "2025-03-05T15:23:08.879Z"
          },
          {
            "key": "visitor_topnav_gql_token",
            "value": "oauth2v2_c26e71b5cc5e2ea077988005de6857a2",
            "expires": "2025-03-06T15:23:01.449Z",
            "domain": "www.upwork.com",
            "path": "/nx/search/jobs",
            "hostOnly": true,
            "creation": "2025-03-05T15:23:08.878Z",
            "lastAccessed": "2025-03-05T15:23:08.878Z"
          },
          {
            "key": "visitor_id",
            "value": "197.221.255.238.1741188174961000",
            "expires": "2025-03-05T16:13:08.874Z",
            "domain": "upwork.com",
            "path": "/",
            "secure": true,
            "hostOnly": false,
            "creation": "2025-03-05T15:23:08.880Z",
            "lastAccessed": "2025-03-05T15:23:08.880Z"
          },
          {
            "key": "UniversalSearchNuxt_vt",
            "value": "oauth2v2_6b4d3280a80e4b6b97380340df2debc7",
            "expires": "2025-03-06T15:22:55.825Z",
            "domain": "upwork.com",
            "path": "/",
            "secure": true,
            "hostOnly": false,
            "creation": "2025-03-05T15:23:08.880Z",
            "lastAccessed": "2025-03-05T15:23:08.880Z"
          },
          {
            "key": "country_code",
            "value": "ZW",
            "expires": "2025-03-05T16:13:08.874Z",
            "domain": "upwork.com",
            "path": "/",
            "secure": true,
            "hostOnly": false,
            "creation": "2025-03-05T15:23:08.881Z",
            "lastAccessed": "2025-03-05T15:23:08.881Z"
          },
          {
            "key": "cookie_prefix",
            "expires": "2025-03-05T16:13:08.874Z",
            "domain": "www.upwork.com",
            "path": "/",
            "secure": true,
            "hostOnly": true,
            "creation": "2025-03-05T15:23:08.881Z",
            "lastAccessed": "2025-03-05T15:23:08.881Z"
          },
          {
            "key": "cookie_domain",
            "value": ".upwork.com",
            "expires": "2025-03-05T16:13:08.874Z",
            "domain": "www.upwork.com",
            "path": "/",
            "secure": true,
            "hostOnly": true,
            "creation": "2025-03-05T15:23:08.881Z",
            "lastAccessed": "2025-03-05T15:23:08.881Z"
          },
          {
            "key": "__cf_bm",
            "value": "r3H2aSeleHsTKL1_axKn.L3Tka3XfzvhGZvYXNANYXg-1741188175-1.0.1.1-.V4PalGD9ViVSK4lE4qBWlA_Zh1Zk73VKXWvUyGRDPJUH6rPuTc870FKcXc9W7QJ1fkGKQhIyWFp2ZKraVzZfAZQ9KfSFCxwDqjReeK7K8M",
            "expires": "2025-03-05T15:52:55.826Z",
            "domain": "upwork.com",
            "path": "/",
            "secure": true,
            "httpOnly": true,
            "hostOnly": false,
            "creation": "2025-03-05T15:23:08.882Z",
            "lastAccessed": "2025-03-05T15:23:08.882Z"
          },
          {
            "key": "__cflb",
            "value": "02DiuEXPXZVk436fJfSVuuwDqLqkhavJbVohcDvHC8LVR",
            "expires": "2025-03-12T15:22:55.826Z",
            "domain": "www.upwork.com",
            "path": "/",
            "secure": true,
            "httpOnly": true,
            "hostOnly": true,
            "creation": "2025-03-05T15:23:08.882Z",
            "lastAccessed": "2025-03-05T15:23:08.882Z"
          },
          {
            "key": "umq",
            "value": "1920",
            "expires": "2025-09-01T15:22:58.625Z",
            "domain": "upwork.com",
            "path": "/",
            "secure": true,
            "hostOnly": false,
            "creation": "2025-03-05T15:23:08.882Z",
            "lastAccessed": "2025-03-05T15:23:08.882Z"
          },
          {
            "key": "AWSALBTG",
            "value": "ICubr4tPfYCincUjdmH/WsYsZkruGWXydes1w4oaAZKwKx4bWAFJw6QjzqB4tDn2FYyglmZc/r7cuLKte3Ce3ZPlNTMohBf1rNUhdoHDaAqJjVOc8v8CAgpGoXo1LRjzfY4ukS6lfIxR8+A7zVW3QrAeXxePIvmM/YpW11m/P0vG",
            "expires": "2025-03-12T15:23:00.912Z",
            "domain": "www.upwork.com",
            "path": "/",
            "hostOnly": true,
            "creation": "2025-03-05T15:23:08.882Z",
            "lastAccessed": "2025-03-05T15:23:08.882Z"
          },
          {
            "key": "AWSALBTGCORS",
            "value": "ICubr4tPfYCincUjdmH/WsYsZkruGWXydes1w4oaAZKwKx4bWAFJw6QjzqB4tDn2FYyglmZc/r7cuLKte3Ce3ZPlNTMohBf1rNUhdoHDaAqJjVOc8v8CAgpGoXo1LRjzfY4ukS6lfIxR8+A7zVW3QrAeXxePIvmM/YpW11m/P0vG",
            "expires": "2025-03-12T15:23:00.912Z",
            "domain": "www.upwork.com",
            "path": "/",
            "secure": true,
            "hostOnly": true,
            "creation": "2025-03-05T15:23:08.883Z",
            "lastAccessed": "2025-03-05T15:23:08.883Z"
          },
          {
            "key": "cf_clearance",
            "value": "EsdVH6KBeR_L94rc1cMtLJSIfmeONoRzGl6evpJyjJI-1741188181-1.2.1.1-LkHzK.pG_6IkzBba4G8GV6uVoySifbSg1Zzxq8Ylznl_WujhupjnTVx18xk0iwFcjkuzFmGB2W8MJqFq.P9Ixpl5IEI.ZJcrnpyP368w3wQezveHAdDGU30M9USk4GwLgeN0rdoi3_D6WfyGCt5tmMjJfwyvjoo7CUbSipWhO7VtmNZtfem_uq.0mFAjvDwyxT3sFFS8ab7efGmEJp1aFJo1uzhENRl31wg6uICHtoyTK4PlgcONGgtUd_QkDwoaYZcG0XZzwXFYO_sewCZvagofl.7vVMTlEAfLQm4gn6yryDYsK8FnUvnnDUOOK5_L7daC6YluGhnbnh38IlqAAy6.hgTyAmWp5OIzPePC7rYmrhbjeiSadbilzjTJWL9rSix3vhuKEYhFgBe8jVE2pSinySxvCnsJoLCDA91g5vo",
            "expires": "2026-03-05T15:23:01.693Z",
            "domain": "upwork.com",
            "path": "/",
            "secure": true,
            "httpOnly": true,
            "hostOnly": false,
            "creation": "2025-03-05T15:23:08.883Z",
            "lastAccessed": "2025-03-05T15:23:08.883Z"
          },
          {
            "key": "_upw_ses.5831",
            "value": "*",
            "expires": "2025-03-05T15:53:03.000Z",
            "domain": "upwork.com",
            "path": "/",
            "secure": true,
            "hostOnly": false,
            "creation": "2025-03-05T15:23:08.883Z",
            "lastAccessed": "2025-03-05T15:23:08.883Z"
          },
          {
            "key": "_cq_duid",
            "value": "1.1741188182.y5eqRnmiEuV6PRmV",
            "expires": "2025-06-04T21:23:02.000Z",
            "domain": "upwork.com",
            "path": "/",
            "secure": true,
            "hostOnly": false,
            "creation": "2025-03-05T15:23:08.884Z",
            "lastAccessed": "2025-03-05T15:23:08.884Z"
          },
          {
            "key": "_cq_suid",
            "value": "1.1741188182.RzYPeQWKq1rNbPnN",
            "expires": "2025-03-05T16:13:08.875Z",
            "domain": "upwork.com",
            "path": "/",
            "secure": true,
            "hostOnly": false,
            "creation": "2025-03-05T15:23:08.884Z",
            "lastAccessed": "2025-03-05T15:23:08.884Z"
          },
          {
            "key": "enabled_ff",
            "value": "CI9570Air2Dot5,air2Dot76,!CI10270Air2Dot5QTAllocations,OTBnrOn,SSINavUserBpa,!air2Dot76Qt,i18nOn,!SSINavUser,!i18nGA,CI17409DarkModeUI,!RMTAir3Talent,!RMTAir3Hired,!RMTAir3Offers,!RMTAir3Offer,!RMTAir3Home,JPAir3,CI11132Air2Dot75,!MP16400Air3Migration,!CI12577UniversalSearch,TONB2256Air3Migration,!CI10857Air3Dot0",
            "expires": "2025-03-05T16:13:08.875Z",
            "domain": "www.upwork.com",
            "path": "/",
            "secure": true,
            "hostOnly": true,
            "creation": "2025-03-05T15:23:08.884Z",
            "lastAccessed": "2025-03-05T15:23:08.884Z"
          },
          {
            "key": "_gcl_au",
            "value": "1.1.1715613201.1741188183",
            "expires": "2025-06-03T15:23:03.000Z",
            "domain": "upwork.com",
            "path": "/",
            "hostOnly": false,
            "creation": "2025-03-05T15:23:08.884Z",
            "lastAccessed": "2025-03-05T15:23:08.884Z"
          },
          {
            "key": "OptanonConsent",
            "value": "isGpcEnabled=0&datestamp=Wed+Mar+05+2025+17%3A23%3A03+GMT%2B0200+(Central+Africa+Time)&version=202305.1.0&browserGpcFlag=0&isIABGlobal=false&hosts=&consentId=edb2fad4-892c-4e79-ba06-92365d24865a&interactionCount=0&landingPath=https%3A%2F%2Fwww.upwork.com%2Fnx%2Fsearch%2Fjobs%2F%3Ffrom_recent_search%3Dtrue%26q%3Dweb%2520developer&groups=C0001%3A1%2CC0002%3A1%2CC0003%3A1%2CC0004%3A1",
            "expires": "2026-03-05T15:23:03.000Z",
            "domain": "upwork.com",
            "path": "/",
            "hostOnly": false,
            "creation": "2025-03-05T15:23:08.885Z",
            "lastAccessed": "2025-03-05T15:23:08.885Z"
          },
          {
            "key": "_upw_id.5831",
            "value": "3199227f-ed24-4d07-aca9-1a82399b748e.1741188182.1.1741188184..a59350d8-9339-4d02-a7be-990a17fa5c8f..0c67af0f-32eb-4937-ac25-d9fdef350717.1741188181716.10",
            "expires": "2026-04-09T15:23:03.715Z",
            "domain": "upwork.com",
            "path": "/",
            "secure": true,
            "hostOnly": false,
            "creation": "2025-03-05T15:23:08.885Z",
            "lastAccessed": "2025-03-05T15:23:08.885Z"
          },
          {
            "key": "_tt_enable_cookie",
            "value": "1",
            "expires": "2026-03-30T15:23:05.000Z",
            "domain": "upwork.com",
            "path": "/",
            "hostOnly": false,
            "creation": "2025-03-05T15:23:08.888Z",
            "lastAccessed": "2025-03-05T15:23:08.888Z"
          },
          {
            "key": "_ttp",
            "value": "01JNKEEF7RB04B765HG5N27NTW_.tt.1",
            "expires": "2026-03-30T15:23:05.000Z",
            "domain": "upwork.com",
            "path": "/",
            "hostOnly": false,
            "creation": "2025-03-05T15:23:08.888Z",
            "lastAccessed": "2025-03-05T15:23:08.888Z"
          },
          {
            "key": "_gcl_au",
            "value": "1.1.1715613201.1741188183",
            "expires": "2025-06-03T15:23:03.000Z",
            "domain": "www.upwork.com",
            "path": "/",
            "hostOnly": true,
            "creation": "2025-03-05T15:23:08.888Z",
            "lastAccessed": "2025-03-05T15:23:08.888Z"
          },
          {
            "key": "forterToken",
            "value": "ee9d7433d3c549328f3fb93ae9a23594_1741188181668__UDF43-m4_23ck_GbTnCB6hvao%3D-1516-v2",
            "expires": "2026-04-09T15:23:06.000Z",
            "domain": "upwork.com",
            "path": "/",
            "hostOnly": false,
            "creation": "2025-03-05T15:23:08.888Z",
            "lastAccessed": "2025-03-05T15:23:08.888Z"
          },
          {
            "key": "forterToken",
            "value": "ee9d7433d3c549328f3fb93ae9a23594_1741188181668__UDF43-m4_23ck_GbTnCB6hvao%3D-1516-v2",
            "expires": "2026-04-09T15:23:06.000Z",
            "domain": "www.upwork.com",
            "path": "/",
            "hostOnly": false,
            "creation": "2025-03-05T15:23:08.888Z",
            "lastAccessed": "2025-03-05T15:23:08.888Z"
          },
          {
            "key": "_fbp",
            "value": "fb.1.1741188186805.106148208370241440",
            "expires": "2025-06-03T15:23:06.000Z",
            "domain": "upwork.com",
            "path": "/",
            "hostOnly": false,
            "creation": "2025-03-05T15:23:08.889Z",
            "lastAccessed": "2025-03-05T15:23:08.889Z"
          },
          {
            "key": "_uetsid",
            "value": "bd465340f9d511efaf2735d722252a9f",
            "expires": "2025-03-06T15:23:07.000Z",
            "domain": "upwork.com",
            "path": "/",
            "hostOnly": false,
            "creation": "2025-03-05T15:23:08.889Z",
            "lastAccessed": "2025-03-05T15:23:08.889Z"
          },
          {
            "key": "_uetvid",
            "value": "bd465090f9d511efba71a36c5a5cdc59",
            "expires": "2026-03-30T15:23:07.000Z",
            "domain": "upwork.com",
            "path": "/",
            "hostOnly": false,
            "creation": "2025-03-05T15:23:08.889Z",
            "lastAccessed": "2025-03-05T15:23:08.889Z"
          },
          {
            "key": "_uetsid",
            "value": "bd465340f9d511efaf2735d722252a9f",
            "expires": "2025-03-06T15:23:07.000Z",
            "domain": "www.upwork.com",
            "path": "/",
            "hostOnly": true,
            "creation": "2025-03-05T15:23:08.889Z",
            "lastAccessed": "2025-03-05T15:23:08.889Z"
          },
          {
            "key": "_uetvid",
            "value": "bd465090f9d511efba71a36c5a5cdc59",
            "expires": "2026-03-30T15:23:07.000Z",
            "domain": "www.upwork.com",
            "path": "/",
            "hostOnly": true,
            "creation": "2025-03-05T15:23:08.889Z",
            "lastAccessed": "2025-03-05T15:23:08.889Z"
          }
        ]
      },
      "userData": {},
      "maxErrorScore": 3,
      "errorScoreDecrement": 0.5,
      "expiresAt": "2025-03-05T16:12:21.628Z",
      "createdAt": "2025-03-05T15:22:21.628Z",
      "usageCount": 3,
      "maxUsageCount": 50,
      "errorScore": 0
    },
    {
      "id": "session_HESRd9enJQ",
      "cookieJar": {
        "version": "tough-cookie@5.1.2",
        "storeType": "MemoryCookieStore",
        "rejectPublicSuffixes": true,
        "enableLooseMode": false,
        "allowSpecialUseDomain": true,
        "prefixSecurity": "silent",
        "cookies": []
      },
      "userData": {},
      "maxErrorScore": 3,
      "errorScoreDecrement": 0.5,
      "expiresAt": "2025-03-05T16:12:54.600Z",
      "createdAt": "2025-03-05T15:22:54.600Z",
      "usageCount": 0,
      "maxUsageCount": 50,
      "errorScore": 0
    }
  ]
}